[
	{
		"inputs": [
			{
				"internalType": "address",
				"name": "_address",
				"type": "address"
			},
			{
				"internalType": "bytes32",
				"name": "role",
				"type": "bytes32"
			}
		],
		"name": "addRole",
		"outputs": [],
		"stateMutability": "nonpayable",
		"type": "function"
	},
	{
		"inputs": [
			{
				"internalType": "uint256",
				"name": "_id",
				"type": "uint256"
			}
		],
		"name": "deleteRecById",
		"outputs": [],
		"stateMutability": "nonpayable",
		"type": "function"
	},
	{
		"inputs": [
			{
				"internalType": "uint256",
				"name": "_idLop",
				"type": "uint256"
			},
			{
				"internalType": "bytes32",
				"name": "_tenMon",
				"type": "bytes32"
			},
			{
				"internalType": "uint256",
				"name": "_idSV",
				"type": "uint256"
			},
			{
				"internalType": "bytes32",
				"name": "_tenSV",
				"type": "bytes32"
			},
			{
				"internalType": "uint256",
				"name": "_idGV",
				"type": "uint256"
			},
			{
				"internalType": "bytes32",
				"name": "_tenGV",
				"type": "bytes32"
			},
			{
				"internalType": "uint256",
				"name": "_diemTH",
				"type": "uint256"
			},
			{
				"internalType": "uint256",
				"name": "_diemGK",
				"type": "uint256"
			},
			{
				"internalType": "uint256",
				"name": "_diemCK",
				"type": "uint256"
			}
		],
		"name": "insertRec",
		"outputs": [],
		"stateMutability": "nonpayable",
		"type": "function"
	},
	{
		"inputs": [
			{
				"components": [
					{
						"internalType": "uint256",
						"name": "idRec",
						"type": "uint256"
					},
					{
						"internalType": "uint256",
						"name": "idLop",
						"type": "uint256"
					},
					{
						"internalType": "bytes32",
						"name": "tenMon",
						"type": "bytes32"
					},
					{
						"internalType": "uint256",
						"name": "idSV",
						"type": "uint256"
					},
					{
						"internalType": "bytes32",
						"name": "tenSV",
						"type": "bytes32"
					},
					{
						"internalType": "uint256",
						"name": "idGV",
						"type": "uint256"
					},
					{
						"internalType": "bytes32",
						"name": "tenGV",
						"type": "bytes32"
					},
					{
						"internalType": "uint256",
						"name": "diemTH",
						"type": "uint256"
					},
					{
						"internalType": "uint256",
						"name": "diemGK",
						"type": "uint256"
					},
					{
						"internalType": "uint256",
						"name": "diemCK",
						"type": "uint256"
					}
				],
				"internalType": "struct Diem.Record[]",
				"name": "record2",
				"type": "tuple[]"
			}
		],
		"name": "insertRec2",
		"outputs": [],
		"stateMutability": "nonpayable",
		"type": "function"
	},
	{
		"inputs": [
			{
				"internalType": "uint256",
				"name": "_id",
				"type": "uint256"
			},
			{
				"internalType": "uint256",
				"name": "_idLop",
				"type": "uint256"
			},
			{
				"internalType": "bytes32",
				"name": "_tenMon",
				"type": "bytes32"
			},
			{
				"internalType": "uint256",
				"name": "_idSV",
				"type": "uint256"
			},
			{
				"internalType": "bytes32",
				"name": "_tenSV",
				"type": "bytes32"
			},
			{
				"internalType": "uint256",
				"name": "_idGV",
				"type": "uint256"
			},
			{
				"internalType": "bytes32",
				"name": "_tenGV",
				"type": "bytes32"
			},
			{
				"internalType": "uint256",
				"name": "_diemTH",
				"type": "uint256"
			},
			{
				"internalType": "uint256",
				"name": "_diemGK",
				"type": "uint256"
			},
			{
				"internalType": "uint256",
				"name": "_diemCK",
				"type": "uint256"
			}
		],
		"name": "updateRecById",
		"outputs": [],
		"stateMutability": "nonpayable",
		"type": "function"
	},
	{
		"inputs": [
			{
				"internalType": "address",
				"name": "_address",
				"type": "address"
			}
		],
		"name": "checkRole",
		"outputs": [
			{
				"internalType": "bytes32",
				"name": "",
				"type": "bytes32"
			}
		],
		"stateMutability": "view",
		"type": "function"
	},
	{
		"inputs": [
			{
				"internalType": "uint256",
				"name": "_id",
				"type": "uint256"
			}
		],
		"name": "findInd",
		"outputs": [
			{
				"internalType": "uint256",
				"name": "",
				"type": "uint256"
			}
		],
		"stateMutability": "view",
		"type": "function"
	},
	{
		"inputs": [],
		"name": "get",
		"outputs": [
			{
				"components": [
					{
						"internalType": "uint256",
						"name": "idRec",
						"type": "uint256"
					},
					{
						"internalType": "uint256",
						"name": "idLop",
						"type": "uint256"
					},
					{
						"internalType": "bytes32",
						"name": "tenMon",
						"type": "bytes32"
					},
					{
						"internalType": "uint256",
						"name": "idSV",
						"type": "uint256"
					},
					{
						"internalType": "bytes32",
						"name": "tenSV",
						"type": "bytes32"
					},
					{
						"internalType": "uint256",
						"name": "idGV",
						"type": "uint256"
					},
					{
						"internalType": "bytes32",
						"name": "tenGV",
						"type": "bytes32"
					},
					{
						"internalType": "uint256",
						"name": "diemTH",
						"type": "uint256"
					},
					{
						"internalType": "uint256",
						"name": "diemGK",
						"type": "uint256"
					},
					{
						"internalType": "uint256",
						"name": "diemCK",
						"type": "uint256"
					}
				],
				"internalType": "struct Diem.Record[]",
				"name": "",
				"type": "tuple[]"
			}
		],
		"stateMutability": "view",
		"type": "function"
	},
	{
		"inputs": [],
		"name": "getLength",
		"outputs": [
			{
				"internalType": "uint256",
				"name": "",
				"type": "uint256"
			}
		],
		"stateMutability": "view",
		"type": "function"
	},
	{
		"inputs": [
			{
				"internalType": "uint256",
				"name": "_id",
				"type": "uint256"
			}
		],
		"name": "getRecById",
		"outputs": [
			{
				"internalType": "uint256",
				"name": "",
				"type": "uint256"
			},
			{
				"internalType": "uint256",
				"name": "",
				"type": "uint256"
			},
			{
				"internalType": "bytes32",
				"name": "",
				"type": "bytes32"
			},
			{
				"internalType": "uint256",
				"name": "",
				"type": "uint256"
			},
			{
				"internalType": "bytes32",
				"name": "",
				"type": "bytes32"
			},
			{
				"internalType": "uint256",
				"name": "",
				"type": "uint256"
			},
			{
				"internalType": "bytes32",
				"name": "",
				"type": "bytes32"
			},
			{
				"internalType": "uint256",
				"name": "",
				"type": "uint256"
			},
			{
				"internalType": "uint256",
				"name": "",
				"type": "uint256"
			},
			{
				"internalType": "uint256",
				"name": "",
				"type": "uint256"
			}
		],
		"stateMutability": "view",
		"type": "function"
	},
	{
		"inputs": [
			{
				"internalType": "uint256",
				"name": "j",
				"type": "uint256"
			}
		],
		"name": "getRecByInd",
		"outputs": [
			{
				"internalType": "uint256",
				"name": "",
				"type": "uint256"
			},
			{
				"internalType": "uint256",
				"name": "",
				"type": "uint256"
			},
			{
				"internalType": "bytes32",
				"name": "",
				"type": "bytes32"
			},
			{
				"internalType": "uint256",
				"name": "",
				"type": "uint256"
			},
			{
				"internalType": "bytes32",
				"name": "",
				"type": "bytes32"
			},
			{
				"internalType": "uint256",
				"name": "",
				"type": "uint256"
			},
			{
				"internalType": "bytes32",
				"name": "",
				"type": "bytes32"
			},
			{
				"internalType": "uint256",
				"name": "",
				"type": "uint256"
			},
			{
				"internalType": "uint256",
				"name": "",
				"type": "uint256"
			},
			{
				"internalType": "uint256",
				"name": "",
				"type": "uint256"
			}
		],
		"stateMutability": "view",
		"type": "function"
	},
	{
		"inputs": [
			{
				"internalType": "uint256",
				"name": "",
				"type": "uint256"
			}
		],
		"name": "record",
		"outputs": [
			{
				"internalType": "uint256",
				"name": "idRec",
				"type": "uint256"
			},
			{
				"internalType": "uint256",
				"name": "idLop",
				"type": "uint256"
			},
			{
				"internalType": "bytes32",
				"name": "tenMon",
				"type": "bytes32"
			},
			{
				"internalType": "uint256",
				"name": "idSV",
				"type": "uint256"
			},
			{
				"internalType": "bytes32",
				"name": "tenSV",
				"type": "bytes32"
			},
			{
				"internalType": "uint256",
				"name": "idGV",
				"type": "uint256"
			},
			{
				"internalType": "bytes32",
				"name": "tenGV",
				"type": "bytes32"
			},
			{
				"internalType": "uint256",
				"name": "diemTH",
				"type": "uint256"
			},
			{
				"internalType": "uint256",
				"name": "diemGK",
				"type": "uint256"
			},
			{
				"internalType": "uint256",
				"name": "diemCK",
				"type": "uint256"
			}
		],
		"stateMutability": "view",
		"type": "function"
	}
]